geosh/__init__.py
geosh-0.1.9.data/data/cy_theoretical_dc.cp311-win_amd64.pyd
geosh-0.1.9.data/data/cy_theoretical_dc.cp312-win_amd64.pyd
geosh-0.1.9.dist-info/LICENSE
geosh-0.1.9.dist-info/LICENSE.txt
geosh-0.1.9.dist-info/METADATA
geosh-0.1.9.dist-info/WHEEL
geosh-0.1.9.dist-info/top_level.txt
geosh-0.1.9.dist-info/RECORD
