Metadata-Version: 2.1
Name: geosh
Version: 0.1.9
Summary: Library and dependency for Geo Utilities Plugin
Home-page: https://github.com/Adre17/geosh
Author: Umberto Grechi
Author-email: umberto.grechi@sofhare.com
Classifier: Programming Language :: Python :: 3.11
Classifier: Programming Language :: Python :: 3.12
Classifier: License :: OSI Approved :: GNU General Public License v3 (GPLv3)
Classifier: Operating System :: OS Independent
Requires-Python: >=3.11, <3.13
License-File: LICENSE
License-File: LICENSE.txt
Requires-Dist: xlrd
Requires-Dist: pyproj
Requires-Dist: numpy
Requires-Dist: shapely
Requires-Dist: matplotlib
Requires-Dist: Pillow
Requires-Dist: psycopg2
Requires-Dist: reportlab
Requires-Dist: segyio
Requires-Dist: opencv-python
Requires-Dist: openpyxl
Requires-Dist: opencv-contrib-python
